h5features/_core.pyi
h5features/libh5features.dylib
h5features/__init__.py
h5features/_core.abi3.so
h5features/py.typed
h5features/.dylibs/libhdf5.310.5.1.dylib
h5features/.dylibs/libaec.0.1.4.dylib
h5features/.dylibs/libsz.2.0.1.dylib
h5features-2.0.0.dist-info/RECORD
h5features-2.0.0.dist-info/WHEEL
h5features-2.0.0.dist-info/METADATA
h5features-2.0.0.dist-info/licenses/LICENSE.txt
